<?xml version="1.0" encoding="UTF-8"?>
<!--Sample XML file generated by XMLSpy v2008 rel. 2 sp2 (http://www.altova.com)-->
<UpdateUserRequest xmlns="urn:tyler:efm:services:schema:UpdateUserRequest" xmlns:xsi="http://www.w3.org/2001/XMLSchema-instance" xmlns:common="urn:tyler:efm:services:schema:Common" xsi:schemaLocation="urn:tyler:efm:services:schema:UpdateUserRequest ..\..\..\Schema\Admin\UpdateUserRequest.xsd">
	<common:User UserID="C542A346-F1E3-4A7B-90B7-4C83C485ACED">
		<common:Email>john.doe@tylertech.com</common:Email>
		<common:FirstName>John</common:FirstName>
		<common:MiddleName/>
		<common:LastName>Doe</common:LastName>
	</common:User>
</UpdateUserRequest>
